helm_mkdocs/__init__.py
helm_mkdocs/chart_processor.py
helm_mkdocs/main.py
helm_mkdocs/version.py
helm_mkdocs/generator/__init__.py
helm_mkdocs/generator/mkdocs/MKDocsGenerator.py
helm_mkdocs/generator/mkdocs/__init__.py
helm_mkdocs/model/__init__.py
helm_mkdocs/model/chart.py
helm_mkdocs/model/page.py
helm_mkdocs/model/token.py
helm_mkdocs/model/yaml_item.py
helm_mkdocs/reader/__init__.py
helm_mkdocs/reader/yaml_reader.py
helm_mkdocs-0.0.5.dist-info/METADATA
helm_mkdocs-0.0.5.dist-info/WHEEL
helm_mkdocs-0.0.5.dist-info/entry_points.txt
helm_mkdocs-0.0.5.dist-info/RECORD
